discovery/__init__.py
discovery/client.py
discovery/crontab.py
discovery/util.py
python_discovery_client-0.5.dist-info/DESCRIPTION.rst
python_discovery_client-0.5.dist-info/METADATA
python_discovery_client-0.5.dist-info/RECORD
python_discovery_client-0.5.dist-info/WHEEL
python_discovery_client-0.5.dist-info/metadata.json
python_discovery_client-0.5.dist-info/top_level.txt
