Metadata-Version: 2.0
Name: python-discovery-client
Version: 0.5
Summary: python client for discovery a registry for resilient mid-tier load balancing and failover. https://github.com/bilibili/discovery
Home-page: https://github.com/tomwei7/discovery-client
Author: tomwei7
Author-email: tomwei7g@gmail.com
License: MIT
Platform: UNKNOWN
Classifier: License :: OSI Approved :: MIT License
Classifier: Programming Language :: Python
Classifier: Programming Language :: Python :: 2
Classifier: Programming Language :: Python :: 2.7
Classifier: Programming Language :: Python :: 3
Classifier: Programming Language :: Python :: 3.4
Classifier: Programming Language :: Python :: 3.5
Classifier: Programming Language :: Python :: 3.6
Classifier: Programming Language :: Python :: 3.7
Requires-Python: >=2.7,!=3.0.*,!=3.1.*,!=3.2.*,!=3.3.*
Requires-Dist: future
